xintesis/__init__.py
xintesis/__main__.py
xintesis/core.py
xintesis/engine.py
xintesis/manager.py
xintesis/template/__init__.py
xintesis/template/default.py
xintesis/template/project.py
xintesis-0.1.dist-info/LICENSE
xintesis-0.1.dist-info/METADATA
xintesis-0.1.dist-info/WHEEL
xintesis-0.1.dist-info/top_level.txt
xintesis-0.1.dist-info/RECORD
