Metadata-Version: 2.1
Name: xintesis
Version: 0.1
Summary: Simple Python Flask based REST API builder
Home-page: https://github.com/J41R0/Xintesis
Author: Jairo Lefebre
Author-email: jairo.lefebre@gmail.com
License: UNKNOWN
Platform: UNKNOWN
Classifier: Programming Language :: Python :: 3
Classifier: License :: OSI Approved :: MIT License
Classifier: Operating System :: OS Independent
Requires-Python: >=3.6
